comsel/__init__.py
comsel/port_select.py
comsel-2.0.0.dist-info/LICENSE
comsel-2.0.0.dist-info/METADATA
comsel-2.0.0.dist-info/WHEEL
comsel-2.0.0.dist-info/top_level.txt
comsel-2.0.0.dist-info/RECORD
