Metadata-Version: 2.1
Name: comsel
Version: 2.0.0
Summary: A Python library for selecting COM port and baudrate
Home-page: https://github.com/Molisc/comsel
Author: Molisc
Author-email: ivanrudko445@gmail.com
Classifier: Programming Language :: Python :: 3
Classifier: License :: OSI Approved :: MIT License
Classifier: Operating System :: OS Independent
Requires-Python: >=3.6
License-File: LICENSE
Requires-Dist: pyserial
Requires-Dist: dearpygui
